libtinyobjloader.so.1
libspdlog.so.1.11.0
utils_bindings.cpython-311-x86_64-linux-gnu.so
libtinyobjloader.so.1.0.4
libUtilsCpp.so
libspdlog.so.1.11
libspdlog.so
libtinyobjloader.so
wp_utils-0.2.11.dist-info/WHEEL
wp_utils-0.2.11.dist-info/top_level.txt
wp_utils-0.2.11.dist-info/RECORD
wp_utils-0.2.11.dist-info/METADATA
utils/__init__.py
