Metadata-Version: 2.1
Name: wp-utils
Version: 0.2.11
Summary: A small C/C++ helper library
Home-page: https://github.com/wpumacay/tiny_utils
Author: Wilbert Santos Pumacay Huallpa
Author-email: wpumacay@gmail.com
License: MIT License
Keywords: C C++ Utils
Classifier: License :: OSI Approved :: MIT License
Classifier: Operating System :: POSIX :: Linux
Requires-Python: >=3.7
